django_partitioned_audit/__init__.py
django_partitioned_audit/admin.py
django_partitioned_audit/apps.py
django_partitioned_audit/models.py
django_partitioned_audit/signals.py
django_partitioned_audit/utils.py
django_partitioned_audit/audit_table/__init__.py
django_partitioned_audit/audit_table/advanced_audit_table_manager.original.sql
django_partitioned_audit/audit_table/advanced_audit_table_manager.py
django_partitioned_audit/audit_table/advanced_audit_table_manager.sql
django_partitioned_audit/audit_table/audit_table_manager.py
django_partitioned_audit/audit_table/simple_audit_table_manager.py
django_partitioned_audit/management/__init__.py
django_partitioned_audit/management/commands/__init__.py
django_partitioned_audit/management/commands/manage_partition_tables.py
django_partitioned_audit/partitions/__init__.py
django_partitioned_audit/partitions/partition_info.py
django_partitioned_audit/partitions/partition_manager_base.py
django_partitioned_audit/partitions/partition_manager_plan.py
django_partitioned_audit/partitions/partition_manager_time_range.py
django_partitioned_audit/partitions/time_range_partitioning.py
django_partitioned_audit-1.0.4.dist-info/LICENSE
django_partitioned_audit-1.0.4.dist-info/METADATA
django_partitioned_audit-1.0.4.dist-info/WHEEL
django_partitioned_audit-1.0.4.dist-info/top_level.txt
django_partitioned_audit-1.0.4.dist-info/RECORD
